latab/__init__.py
latab/columns.py
latab/converter.py
latab/errors.py
latab/formatters.py
latab/table.py
latab-1.0.6.dist-info/LICENSE
latab-1.0.6.dist-info/METADATA
latab-1.0.6.dist-info/WHEEL
latab-1.0.6.dist-info/top_level.txt
latab-1.0.6.dist-info/RECORD
