Metadata-Version: 2.1
Name: latab
Version: 1.0.6
Summary: Tool to easily convert numpy arrays into latex tables with astropy units support.
Author-email: Balázs Klement <astro@bklement.com>
Project-URL: Homepage, https://github.com/bklement/latab
Project-URL: Bug Tracker, https://github.com/bklement/latab/issues
Classifier: Programming Language :: Python :: 3 :: Only
Classifier: License :: OSI Approved :: MIT License
Classifier: Operating System :: OS Independent
Classifier: Development Status :: 5 - Production/Stable
Requires-Python: >=3.7
License-File: LICENSE
Requires-Dist: numpy
Requires-Dist: astropy
